Workbook

Sheet Dashboard
B1: MyClearBudget — Dashboard
B2: BRRRR Strategy Calculator
B3: Buy · Rehab · Rent · Refinance · Repeat — Trailhead Standard
B6: Initial Cash Invested | D6: After Repair Value (ARV) | F6: Refinance Loan Amount
B7: ='Refinance Analysis'!D17 | D7: ='Refinance Analysis'!D7 | F7: ='Refinance Analysis'!D9
B9: Cash Pulled Out | D9: Equity Remaining | F9: Monthly Cash Flow
B10: ='Refinance Analysis'!D18 | D10: ='Refinance Analysis'!D20 | F10: ='Cash Flow Analysis'!D11
B12: Annual Cash Flow | D12: Cash-on-Cash Return | F12: Infinite Return?
B13: ='Cash Flow Analysis'!D12 | D13: =IF('Refinance Analysis'!D19<=0,"Infinite",IF('Refinance Analysis'!D19>0,'Cash Flow Analysis'!D12/'Refinance Analysis'!D19,0)) | F13: =IF('Refinance Analysis'!D19<=0,"YES","No")
H15: Category | I15: Amount
H16: Initial Cash Invested | I16: ='Refinance Analysis'!D17
H17: Cash Pulled Out | I17: ='Refinance Analysis'!D18
H18: Equity Remaining | I18: ='Refinance Analysis'!D20

Sheet Purchase & Rehab
B1: MyClearBudget — Purchase & Rehab
B2: BRRRR Strategy Calculator
B3: Purchase & Rehab — Step 1: What did you buy and invest?
B5: ACQUISITION COSTS
B6: Enter yellow cells. Blue cells calculate automatically.
B7: Purchase Price | D7: 120000 | F7: The price you paid for the property
B8: Purchase Closing Costs | D8: 3000 | F8: Title, escrow, lender fees, etc.
B10: REHAB & RENOVATION
B11: Enter your rehab budget. Contingency is calculated automatically.
B12: Rehab / Renovation Budget | D12: 35000 | F12: Total estimated renovation costs
B13: Contingency % | D13: 0.1 | F13: Buffer for overruns (10% recommended)
B14: Contingency Amount | D14: ='Purchase & Rehab'!D12*'Purchase & Rehab'!D13 | F14: Auto-calculated
B16: INITIAL FINANCING (Optional — leave 0 for cash purchase)
B17: If you used hard money or a loan for acquisition, enter details here.
B18: Down Payment % | D18: 0 | F18: 0% = all-cash purchase
B19: Initial Loan Amount | D19: ='Purchase & Rehab'!D7*(1-'Purchase & Rehab'!D18) | F19: Auto-calculated
B20: Hard Money Rate % | D20: 0.12 | F20: Annual interest rate
B21: Hard Money Term (months) | D21: 12 | F21: Typical 6–18 months
B22: Monthly Hard Money Payment | D22: =IF('Purchase & Rehab'!D19>0,PMT('Purchase & Rehab'!D20/12,'Purchase & Rehab'!D21,-'Purchase & Rehab'!D19),0) | F22: Auto-calculated (PMT)
B24: TOTAL PROJECT COST | E24: ='Purchase & Rehab'!D7+'Purchase & Rehab'!D8+'Purchase & Rehab'!D12+'Purchase & Rehab'!D14

Sheet Rental Income & Expenses
B1: MyClearBudget — Rental Income & Expenses
B2: BRRRR Strategy Calculator
B3: Rental Income & Expenses — Step 2: What will the property generate?
B5: RENTAL INCOME
B6: Enter yellow cells. Blue cells calculate automatically.
B7: Monthly Gross Rent | D7: 1650 | F7: Full market rent (no vacancy deduction)
B8: Vacancy Rate % | D8: 0.05 | F8: Industry standard: 5–10%
B9: Effective Gross Income / Month | D9: ='Rental Income & Expenses'!D7*(1-'Rental Income & Expenses'!D8) | F9: Gross Rent minus vacancy
B11: MONTHLY OPERATING EXPENSES
B12: Enter monthly amounts. Mgmt, Maintenance, and CapEx are % of gross rent.
B13: Property Management % | D13: 0.08 | F13: % of gross rent (8% standard)
B14: Property Management $ | D14: ='Rental Income & Expenses'!D7*'Rental Income & Expenses'!D13 | F14: Auto-calculated
B15: Property Taxes (monthly) | D15: 175 | F15: Check county records
B16: Insurance (monthly) | D16: 120 | F16: Landlord / dwelling policy
B17: HOA (monthly) | D17: 0 | F17: If applicable
B18: Maintenance Reserve % | D18: 0.01 | F18: % of ARV/year — use Refinance tab ARV
B19: Maintenance Reserve $ / Month | D19: ='Refinance Analysis'!D7*'Rental Income & Expenses'!D18/12 | F19: 1% of ARV per year
B20: CapEx Reserve % | D20: 0.01 | F20: % of ARV/year — capital expenditures
B21: CapEx Reserve $ / Month | D21: ='Refinance Analysis'!D7*'Rental Income & Expenses'!D20/12 | F21: 1% of ARV per year
B22: Other Expenses (monthly) | D22: 0 | F22: Utilities, lawn care, etc.
B24: Total Monthly Expenses | D24: ='Rental Income & Expenses'!D14+'Rental Income & Expenses'!D15+'Rental Income & Expenses'!D16+'Rental Income & Expenses'!D17+'Rental Income & Expenses'!D19+'Rental Income & Expenses'!D21+'Rental Income & Expenses'!D22 | F24: Sum of all expenses above
B26: NET OPERATING INCOME
B27: Net Operating Income / Month | D27: ='Rental Income & Expenses'!D9-'Rental Income & Expenses'!D24 | F27: EGI minus all operating expenses
B28: Net Operating Income / Year | D28: ='Rental Income & Expenses'!D27*12 | F28: Annual NOI
B29: Cap Rate | D29: =IF('Refinance Analysis'!D7>0,'Rental Income & Expenses'!D28/'Refinance Analysis'!D7,0) | F29: Annual NOI / ARV

Sheet Refinance Analysis
B1: MyClearBudget — Refinance Analysis
B2: BRRRR Strategy Calculator
B3: Refinance Analysis — Step 3: What will the lender give you?
B5: PROPERTY VALUE & LOAN TERMS
B6: Enter yellow cells. Blue cells calculate automatically.
B7: After Repair Value (ARV) | D7: 195000 | F7: Supported by comparable sales
B8: Lender LTV % | D8: 0.75 | F8: 75% standard for investment property
B9: Refinance Loan Amount | D9: ='Refinance Analysis'!D7*'Refinance Analysis'!D8 | F9: ARV x LTV
B10: Refinance Closing Costs | D10: 4500 | F10: Typical 2–3% of loan amount
B11: Refinance Interest Rate % | D11: 0.0725 | F11: Current market rate
B12: Refinance Loan Term (years) | D12: 30 | F12: 30-year standard
B13: Monthly Refinance Payment | D13: =PMT('Refinance Analysis'!D11/12,'Refinance Analysis'!D12*12,-'Refinance Analysis'!D9) | F13: Auto-calculated (PMT)
B15: CASH RECOVERY ANALYSIS
B16: How much of your investment did you pull back out?
B17: Total Cash Invested | D17: ='Purchase & Rehab'!D7+'Purchase & Rehab'!D8+'Purchase & Rehab'!D12+'Purchase & Rehab'!D14-'Purchase & Rehab'!D19 | F17: Purchase + Closing + Rehab + Contingency - Initial Loan
B18: Cash Pulled Out at Refinance | D18: ='Refinance Analysis'!D9-'Purchase & Rehab'!D19-'Refinance Analysis'!D10 | F18: Refi Loan - Existing Loan Payoff - Refi Closing Costs
B19: Cash Left in Deal | D19: ='Refinance Analysis'!D17-'Refinance Analysis'!D18 | F19: Total Invested minus Cash Pulled Out
B20: Equity Remaining (ARV - Loan) | D20: ='Refinance Analysis'!D7-'Refinance Analysis'!D9 | F20: Your equity position after refinance
B22: INFINITE RETURN? | E22: =IF('Refinance Analysis'!D19<=0,"YES — Infinite Return!","No — Cash Remaining in Deal")

Sheet Cash Flow Analysis
B1: MyClearBudget — Cash Flow Analysis
B2: BRRRR Strategy Calculator
B3: Cash Flow Analysis — Step 4: What does the deal generate post-refinance?
B5: POST-REFINANCE CASH FLOW
B6: All values pull from other tabs automatically. Review and confirm.
B7: Monthly Rental Income (EGI) | D7: ='Rental Income & Expenses'!D9 | F7: From Rental Income tab
B8: Monthly Refinance Payment | D8: ='Refinance Analysis'!D13 | F8: From Refinance Analysis tab
B9: Monthly Operating Expenses | D9: ='Rental Income & Expenses'!D24 | F9: From Rental Income tab
B11: Monthly Cash Flow | D11: ='Cash Flow Analysis'!D7-'Cash Flow Analysis'!D8-'Cash Flow Analysis'!D9 | F11: Income minus Refi Payment minus Expenses
B12: Annual Cash Flow | D12: ='Cash Flow Analysis'!D11*12 | F12: Monthly x 12
B14: RETURN METRICS
B15: Cash-on-Cash Return | D15: =IF('Refinance Analysis'!D19<=0,"Infinite",IF('Refinance Analysis'!D19>0,'Cash Flow Analysis'!D12/'Refinance Analysis'!D19,0)) | F15: Annual Cash Flow / Cash Left in Deal
B16: Debt Service Coverage Ratio (DSCR) | D16: =IF('Cash Flow Analysis'!D8>0,'Rental Income & Expenses'!D28/('Cash Flow Analysis'!D8*12),0) | F16: NOI / Annual Debt Service (>1.25 required)
B18: MONTHLY CASH FLOW | E18: ='Cash Flow Analysis'!D11

Sheet BRRRR Scorecard
B1: MyClearBudget — BRRRR Scorecard
B2: BRRRR Strategy Calculator
B3: BRRRR Scorecard — Deal at a Glance
B5: DEAL SCORECARD
B7: Metric | C7: Value | D7: Target | E7: Status
B8: After Repair Value (ARV) | C8: ='Refinance Analysis'!D7 | D8: > Purchase + Rehab | E8: =IF('Refinance Analysis'!D7>('Purchase & Rehab'!D7+'Purchase & Rehab'!D12),"PASS","FAIL")
B9: Cash Pulled Out at Refinance | C9: ='Refinance Analysis'!D18 | D9: >= Total Invested | E9: =IF('Refinance Analysis'!D18>='Refinance Analysis'!D17,"PASS","FAIL")
B10: Cash Left in Deal | C10: ='Refinance Analysis'!D19 | D10: < $0 (Infinite Return)
B11: Monthly Cash Flow | C11: ='Cash Flow Analysis'!D11 | D11: > $200 / month | E11: =IF('Cash Flow Analysis'!D11>200,"PASS","FAIL")
B12: DSCR (Debt Service Coverage) | C12: ='Cash Flow Analysis'!D16 | D12: > 1.25x | E12: =IF('Cash Flow Analysis'!D16>1.25,"PASS","FAIL")
B13: Cash-on-Cash Return | C13: =IF('Refinance Analysis'!D19<=0,"Infinite",IF('Refinance Analysis'!D19>0,'Cash Flow Analysis'!D12/'Refinance Analysis'!D19,0)) | D13: > 8% | E13: =IF('Refinance Analysis'!D19<=0,"INFINITE",IF(AND('Refinance Analysis'!D19>0,'Cash Flow Analysis'!D12/'Refinance Analysis'!D19>0.08),"PASS","FAIL"))
B14: Cap Rate | C14: ='Rental Income & Expenses'!D29 | D14: > 6% | E14: =IF('Rental Income & Expenses'!D29>0.06,"PASS","FAIL")
B15: Infinite Return? | C15: ='Refinance Analysis'!D22 | D15: YES — goal | E15: =IF('Refinance Analysis'!D19<=0,"YES","No")
B17: OVERALL DEAL RATING
B19: Deal Rating | E19: =IF((E8="PASS")+(E9="PASS")+(E11="PASS")+(E12="PASS")+(E14="PASS")>=5,"STRONG",IF((E8="PASS")+(E9="PASS")+(E11="PASS")+(E12="PASS")+(E14="PASS")>=4,"GOOD",IF((E8="PASS")+(E9="PASS")+(E11="PASS")+(E12="PASS")+(E14="PASS")>=3,"MARGINAL","PASS")))

Sheet Getting Started
B1: MyClearBudget — Getting Started
B2: BRRRR Strategy Calculator
B3: Getting Started — Read This First
B5: What Is the BRRRR Strategy?
B6: BRRRR stands for Buy, Rehab, Rent, Refinance, Repeat.
B7: The strategy allows real estate investors to recycle their capital by purchasing distressed properties,
B8: renovating them to force appreciation, renting them for cash flow, and then refinancing to pull out
B9: most or all of their initial investment — then repeating the process with the same dollars.
B10: Done correctly, you can build a rental portfolio with limited out-of-pocket capital.
B12: How to Use This Calculator
B13: Step 1 — Purchase & Rehab: Enter your purchase price, closing costs, and renovation budget.
B14: Step 2 — Rental Income & Expenses: Enter projected rents and operating costs.
... B45: Visit trailheadstandard.com for more tools and resources.
